{"boundaryID": "FRA-ADM1-19338628", "boundaryName": "France", "boundaryISO": "FRA", "boundaryYearRepresented": "2022", "boundaryType": "ADM1", "boundaryCanonical": "Region", "boundarySource": "Institut national de l'information g\u00e9ographique et foresti\u00e8re (IGN-F)", "boundaryLicense": "Etalab Open License 2.0", "licenseDetail": "nan", "licenseSource": "geoservices.ign.fr/sites/default/files/2021-11/IGNF_ADMIN_EXPRESS_3-1.html", "boundarySourceURL": "geoservices.ign.fr/adminexpress", "sourceDataUpdateDate": "Thu Jan 19 07:31:04 2023", "buildDate": "Jan 23, 2023", "Continent": "Europe", "UNSDG-region": "Europe and Northern America", "UNSDG-subregion": "Western Europe", "worldBankIncomeGroup": "High-income Countries", "admUnitCount": "13", "meanVertices": "129696.0", "minVertices": "27136", "maxVertices": "422033", "meanPerimeterLengthKM": "2545.152039252083", "minPerimeterLengthKM": "1094.8626354212429", "maxPerimeterLengthKM": "4727.329261287934", "meanAreaSqKM": "42242.50941846597", "minAreaSqKM": "8721.373115656008", "maxAreaSqKM": "85183.83789479267", "staticDownloadLink": "https://github.com/wmgeolab/geoBoundaries/raw/b7dd6a5/releaseData/gbOpen/FRA/ADM1/geoBoundaries-FRA-ADM1-all.zip", "gjDownloadURL": "https://github.com/wmgeolab/geoBoundaries/raw/905b0ba/releaseData/gbOpen/FRA/ADM1/geoBoundaries-FRA-ADM1.geojson", "tjDownloadURL": "https://github.com/wmgeolab/geoBoundaries/raw/905b0ba/releaseData/gbOpen/FRA/ADM1/geoBoundaries-FRA-ADM1.topojson", "imagePreview": "https://github.com/wmgeolab/geoBoundaries/raw/905b0ba/releaseData/gbOpen/FRA/ADM1/geoBoundaries-FRA-ADM1-PREVIEW.png", "simplifiedGeometryGeoJSON": "https://github.com/wmgeolab/geoBoundaries/raw/905b0ba/releaseData/gbOpen/FRA/ADM1/geoBoundaries-FRA-ADM1_simplified.geojson"}