{"boundaryID": "KAZ-ADM0-12445969", "boundaryName": "Kazakhstan", "boundaryISO": "KAZ", "boundaryYearRepresented": "2017", "boundaryType": "ADM0", "boundaryCanonical": "Unknown", "boundarySource": "OpenStreetMap, Wambacher", "boundaryLicense": "Open Data Commons Open Database License 1.0", "licenseDetail": "Open Data Commons Open Database License 1.0", "licenseSource": "www.openstreetmap.org/copyright", "boundarySourceURL": "wambachers-osm.website/boundaries/", "sourceDataUpdateDate": "Thu Jan 19 07:31:04 2023", "buildDate": "Jul 05, 2023", "Continent": "Asia", "UNSDG-region": "Central and Southern Asia", "UNSDG-subregion": "Central Asia", "worldBankIncomeGroup": "Upper-middle-income Countries", "admUnitCount": "1", "meanVertices": "53977.0", "minVertices": "53977", "maxVertices": "53977", "meanPerimeterLengthKM": "20940.19642637488", "minPerimeterLengthKM": "20940.19642637488", "maxPerimeterLengthKM": "20940.19642637488", "meanAreaSqKM": "2706684.552700483", "minAreaSqKM": "2706684.552700483", "maxAreaSqKM": "2706684.552700483", "staticDownloadLink": "https://github.com/wmgeolab/geoBoundaries/raw/9c0f69a/releaseData/gbOpen/KAZ/ADM0/geoBoundaries-KAZ-ADM0-all.zip", "gjDownloadURL": "https://github.com/wmgeolab/geoBoundaries/raw/41af8f1/releaseData/gbOpen/KAZ/ADM0/geoBoundaries-KAZ-ADM0.geojson", "tjDownloadURL": "https://github.com/wmgeolab/geoBoundaries/raw/41af8f1/releaseData/gbOpen/KAZ/ADM0/geoBoundaries-KAZ-ADM0.topojson", "imagePreview": "https://github.com/wmgeolab/geoBoundaries/raw/41af8f1/releaseData/gbOpen/KAZ/ADM0/geoBoundaries-KAZ-ADM0-PREVIEW.png", "simplifiedGeometryGeoJSON": "https://github.com/wmgeolab/geoBoundaries/raw/41af8f1/releaseData/gbOpen/KAZ/ADM0/geoBoundaries-KAZ-ADM0_simplified.geojson"}