{"boundaryID": "GEO-ADM2-92138335", "boundaryName": "Georgia", "boundaryISO": "GEO", "boundaryYearRepresented": "2007", "boundaryType": "ADM2", "boundaryCanonical": "Municipality", "boundarySource": "geoBoundaries, Wikimedia Commons", "boundaryLicense": "Public Domain", "licenseDetail": "nan", "licenseSource": "commons.wikimedia.org/wiki/File", "boundarySourceURL": "commons.wikimedia.org/wiki/File", "sourceDataUpdateDate": "Thu Jan 19 07:31:04 2023", "buildDate": "Jan 23, 2023", "Continent": "Asia", "UNSDG-region": "Northern Africa and Western Asia", "UNSDG-subregion": "Western Asia", "worldBankIncomeGroup": "Lower-middle-income Countries", "admUnitCount": "68", "meanVertices": "1164.0", "minVertices": "485", "maxVertices": "2573", "meanPerimeterLengthKM": "194.2980406591832", "minPerimeterLengthKM": "99.78179908893812", "maxPerimeterLengthKM": "374.20655257116346", "meanAreaSqKM": "1030.6128035184754", "minAreaSqKM": "292.12526991116823", "maxAreaSqKM": "3238.605592565894", "staticDownloadLink": "https://github.com/wmgeolab/geoBoundaries/raw/2d3e29d/releaseData/gbOpen/GEO/ADM2/geoBoundaries-GEO-ADM2-all.zip", "gjDownloadURL": "https://github.com/wmgeolab/geoBoundaries/raw/905b0ba/releaseData/gbOpen/GEO/ADM2/geoBoundaries-GEO-ADM2.geojson", "tjDownloadURL": "https://github.com/wmgeolab/geoBoundaries/raw/905b0ba/releaseData/gbOpen/GEO/ADM2/geoBoundaries-GEO-ADM2.topojson", "imagePreview": "https://github.com/wmgeolab/geoBoundaries/raw/905b0ba/releaseData/gbOpen/GEO/ADM2/geoBoundaries-GEO-ADM2-PREVIEW.png", "simplifiedGeometryGeoJSON": "https://github.com/wmgeolab/geoBoundaries/raw/905b0ba/releaseData/gbOpen/GEO/ADM2/geoBoundaries-GEO-ADM2_simplified.geojson"}