{"boundaryID": "BFA-ADM0-72675738", "boundaryName": "Burkina Faso", "boundaryISO": "BFA", "boundaryYearRepresented": "2017", "boundaryType": "ADM0", "boundaryCanonical": "Burkina Faso", "boundarySource": "GeoBoundaries, World Bank", "boundaryLicense": "Creative Commons Attribution 4.0 (CC BY 4.0)", "licenseDetail": "nan", "licenseSource": "datacatalog.worldbank.org/public-licenses#cc-by", "boundarySourceURL": "datacatalog.worldbank.org/dataset/burkina-faso-administrative-boundaries-2017", "sourceDataUpdateDate": "Thu Jan 19 07:31:04 2023", "buildDate": "Jan 23, 2023", "Continent": "Africa", "UNSDG-region": "Sub-Saharan Africa", "UNSDG-subregion": "Western Africa", "worldBankIncomeGroup": "Low-income Countries", "admUnitCount": "1", "meanVertices": "2223.0", "minVertices": "2223", "maxVertices": "2223", "meanPerimeterLengthKM": "3505.627111595364", "minPerimeterLengthKM": "3505.627111595364", "maxPerimeterLengthKM": "3505.627111595364", "meanAreaSqKM": "273376.53273476305", "minAreaSqKM": "273376.53273476305", "maxAreaSqKM": "273376.53273476305", "staticDownloadLink": "https://github.com/wmgeolab/geoBoundaries/raw/14d4eb3/releaseData/gbOpen/BFA/ADM0/geoBoundaries-BFA-ADM0-all.zip", "gjDownloadURL": "https://github.com/wmgeolab/geoBoundaries/raw/905b0ba/releaseData/gbOpen/BFA/ADM0/geoBoundaries-BFA-ADM0.geojson", "tjDownloadURL": "https://github.com/wmgeolab/geoBoundaries/raw/905b0ba/releaseData/gbOpen/BFA/ADM0/geoBoundaries-BFA-ADM0.topojson", "imagePreview": "https://github.com/wmgeolab/geoBoundaries/raw/905b0ba/releaseData/gbOpen/BFA/ADM0/geoBoundaries-BFA-ADM0-PREVIEW.png", "simplifiedGeometryGeoJSON": "https://github.com/wmgeolab/geoBoundaries/raw/905b0ba/releaseData/gbOpen/BFA/ADM0/geoBoundaries-BFA-ADM0_simplified.geojson"}