{"boundaryID": "MHL-ADM0-89087692", "boundaryName": "Marshall Islands", "boundaryISO": "MHL", "boundaryYearRepresented": "2017", "boundaryType": "ADM0", "boundaryCanonical": "Unknown", "boundarySource": "OpenStreetMap, Wambacher", "boundaryLicense": "Open Data Commons Open Database License 1.0", "licenseDetail": "Open Data Commons Open Database License 1.0", "licenseSource": "www.openstreetmap.org/copyright", "boundarySourceURL": "wambachers-osm.website/boundaries/", "sourceDataUpdateDate": "Thu Jan 19 07:31:04 2023", "buildDate": "Jan 23, 2023", "Continent": "Oceania", "UNSDG-region": "Oceania (excluding Australia and New Zealand)", "UNSDG-subregion": "Micronesia", "worldBankIncomeGroup": "Upper-middle-income Countries", "admUnitCount": "1", "meanVertices": "10020.0", "minVertices": "10020", "maxVertices": "10020", "meanPerimeterLengthKM": "961.2815887488216", "minPerimeterLengthKM": "961.2815887488216", "maxPerimeterLengthKM": "961.2815887488216", "meanAreaSqKM": "125.40964934177198", "minAreaSqKM": "125.40964934177198", "maxAreaSqKM": "125.40964934177198", "staticDownloadLink": "https://github.com/wmgeolab/geoBoundaries/raw/8181b6c/releaseData/gbOpen/MHL/ADM0/geoBoundaries-MHL-ADM0-all.zip", "gjDownloadURL": "https://github.com/wmgeolab/geoBoundaries/raw/905b0ba/releaseData/gbOpen/MHL/ADM0/geoBoundaries-MHL-ADM0.geojson", "tjDownloadURL": "https://github.com/wmgeolab/geoBoundaries/raw/905b0ba/releaseData/gbOpen/MHL/ADM0/geoBoundaries-MHL-ADM0.topojson", "imagePreview": "https://github.com/wmgeolab/geoBoundaries/raw/905b0ba/releaseData/gbOpen/MHL/ADM0/geoBoundaries-MHL-ADM0-PREVIEW.png", "simplifiedGeometryGeoJSON": "https://github.com/wmgeolab/geoBoundaries/raw/905b0ba/releaseData/gbOpen/MHL/ADM0/geoBoundaries-MHL-ADM0_simplified.geojson"}